openqa_log_local/__init__.py
openqa_log_local/cache.py
openqa_log_local/cli.py
openqa_log_local/client.py
openqa_log_local/main.py
openqa_log_local-0.2.1.dist-info/WHEEL
openqa_log_local-0.2.1.dist-info/entry_points.txt
openqa_log_local-0.2.1.dist-info/METADATA
openqa_log_local-0.2.1.dist-info/RECORD
