Metadata-Version: 2.3
Name: openqa-log-local
Version: 0.2.1
Summary: Create a local cache of openQA job log files
Author: Michele Pagot
Author-email: Michele Pagot <michele.pagot@suse.com>
Requires-Dist: openqa-client>=4.3.1
Requires-Dist: click
Requires-Python: >=3.9
